module_tools/__init__.py
module_tools-0.0.3.dist-info/LICENSE
module_tools-0.0.3.dist-info/METADATA
module_tools-0.0.3.dist-info/WHEEL
module_tools-0.0.3.dist-info/top_level.txt
module_tools-0.0.3.dist-info/RECORD
